Metadata-Version: 2.1
Name: gensim-bz2-nsml
Version: 3.8.0
Summary: Python framework for fast Vector Space Modelling
Home-page: http://radimrehurek.com/gensim
Author: Radim Rehurek
Author-email: me@radimrehurek.com
License: LGPLv2.1
Download-URL: http://pypi.python.org/pypi/gensim
Keywords: Singular Value Decomposition,SVD,Latent Semantic Indexing,LSA,LSI,Latent Dirichlet Allocation,LDA,Hierarchical Dirichlet Process,HDP,Random Projections,TFIDF,word2vec
Platform: any
Classifier: Development Status :: 5 - Production/Stable
Classifier: Environment :: Console
Classifier: Intended Audience :: Science/Research
Classifier: License :: OSI Approved :: GNU Lesser General Public License v2 or later (LGPLv2+)
Classifier: Operating System :: OS Independent
Classifier: Programming Language :: Python :: 2.7
Classifier: Programming Language :: Python :: 3.5
Classifier: Programming Language :: Python :: 3.6
Classifier: Programming Language :: Python :: 3.7
Classifier: Topic :: Scientific/Engineering :: Artificial Intelligence
Classifier: Topic :: Scientific/Engineering :: Information Analysis
Classifier: Topic :: Text Processing :: Linguistic
Requires-Dist: numpy (>=1.11.3)
Requires-Dist: scipy (>=0.18.1)
Requires-Dist: six (>=1.5.0)
Requires-Dist: smart-open (>=1.7.0)
Provides-Extra: distributed
Requires-Dist: Pyro4 (>=4.27) ; extra == 'distributed'
Provides-Extra: docs
Requires-Dist: pytest ; extra == 'docs'
Requires-Dist: pytest-rerunfailures ; extra == 'docs'
Requires-Dist: mock ; extra == 'docs'
Requires-Dist: cython ; extra == 'docs'
Requires-Dist: testfixtures ; extra == 'docs'
Requires-Dist: Morfessor (==2.0.2a4) ; extra == 'docs'
Requires-Dist: python-Levenshtein (>=0.10.2) ; extra == 'docs'
Requires-Dist: visdom (!=0.1.8.7,>=0.1.8) ; extra == 'docs'
Requires-Dist: scikit-learn ; extra == 'docs'
Requires-Dist: Pyro4 (>=4.27) ; extra == 'docs'
Requires-Dist: sphinx ; extra == 'docs'
Requires-Dist: sphinxcontrib-napoleon ; extra == 'docs'
Requires-Dist: plotly ; extra == 'docs'
Requires-Dist: pattern (<=2.6) ; extra == 'docs'
Requires-Dist: sphinxcontrib.programoutput ; extra == 'docs'
Provides-Extra: test
Requires-Dist: pytest ; extra == 'test'
Requires-Dist: pytest-rerunfailures ; extra == 'test'
Requires-Dist: mock ; extra == 'test'
Requires-Dist: cython ; extra == 'test'
Requires-Dist: testfixtures ; extra == 'test'
Requires-Dist: Morfessor (==2.0.2a4) ; extra == 'test'
Requires-Dist: python-Levenshtein (>=0.10.2) ; extra == 'test'
Requires-Dist: visdom (!=0.1.8.7,>=0.1.8) ; extra == 'test'
Requires-Dist: scikit-learn ; extra == 'test'
Provides-Extra: test-win
Requires-Dist: pytest ; extra == 'test-win'
Requires-Dist: pytest-rerunfailures ; extra == 'test-win'
Requires-Dist: mock ; extra == 'test-win'
Requires-Dist: cython ; extra == 'test-win'
Requires-Dist: testfixtures ; extra == 'test-win'
Requires-Dist: Morfessor (==2.0.2a4) ; extra == 'test-win'
Requires-Dist: python-Levenshtein (>=0.10.2) ; extra == 'test-win'
Requires-Dist: visdom (!=0.1.8.7,>=0.1.8) ; extra == 'test-win'
Requires-Dist: scikit-learn ; extra == 'test-win'
